keras_gpt/__init__.py
keras_gpt/py.typed
keras_gpt/tokenizer.py
keras_gpt-0.0.1.dev0.dist-info/METADATA
keras_gpt-0.0.1.dev0.dist-info/WHEEL
keras_gpt-0.0.1.dev0.dist-info/licenses/LICENSE
keras_gpt-0.0.1.dev0.dist-info/RECORD
